torch_scatter/__init__.py
torch_scatter/_scatter_cpu.so
torch_scatter/_scatter_cuda.so
torch_scatter/_segment_coo_cpu.so
torch_scatter/_segment_coo_cuda.so
torch_scatter/_segment_csr_cpu.so
torch_scatter/_segment_csr_cuda.so
torch_scatter/_version_cpu.so
torch_scatter/_version_cuda.so
torch_scatter/composite/__init__.py
torch_scatter/composite/logsumexp.py
torch_scatter/composite/softmax.py
torch_scatter/composite/std.py
torch_scatter/placeholder.py
torch_scatter/scatter.py
torch_scatter/segment_coo.py
torch_scatter/segment_csr.py
torch_scatter/testing.py
torch_scatter/utils.py
torch_scatter_rocm-2.1.2.post2.dist-info/LICENSE
torch_scatter_rocm-2.1.2.post2.dist-info/METADATA
torch_scatter_rocm-2.1.2.post2.dist-info/RECORD
torch_scatter_rocm-2.1.2.post2.dist-info/WHEEL
torch_scatter_rocm-2.1.2.post2.dist-info/top_level.txt